README.md
setup.py
Decision_tree_zrq.egg-info/PKG-INFO
Decision_tree_zrq.egg-info/SOURCES.txt
Decision_tree_zrq.egg-info/dependency_links.txt
Decision_tree_zrq.egg-info/top_level.txt
neupy_core_model_api_src/__init__.py
neupy_core_model_api_src/chiMerge.py
neupy_core_model_api_src/oracle2database.py
rsources/__init__.py
scripts/__init__.py